{"name":"Introduce","tagline":"introduce company information.","body":"### Welcome to ZSmarter Introduce.\r\nZSmarter Introduce list.\r\n\r\n***\r\n\r\n### Authors and Contributors\r\nE-mail:[zhaojunming@zsmarter.com](mailto:zhaojunming@zsmarter.com).\r\nCompany: 中天智慧科技有限公司.\r\n\r\n### Support or Contact\r\n [中天智慧科技有限公司](http://www.zsmarter.com) or [contact Z.JM](mailto:zhaojunming@zsmarter.com).\r\n","google":"","note":"Don't delete this file! It's used internally to help with page regeneration."}